{
  "kind": "youtube#searchResult",
  "id": {
    "kind": "youtube#video",
    "videoId": "q34q9HBW5M8"
  },
  "snippet": {
    "publishedAt": "2018-10-01T20:33:38Z",
    "channelId": "UCL_f53ZEJxp8TtlOkHwMV9Q",
    "title": "Next Week: St Louis, Salt Lake City, Colorado Springs",
    "description": "I wanted to specifically highlight a few cities and venues where I will be speaking about 12 Rules for Life (https://jordanbpeterson.com/12-rules-for-life/) from now ...",
    "thumbnails": {
      "default": {
        "url": "https://i.ytimg.com/vi/q34q9HBW5M8/default.jpg",
        "width": 120,
        "height": 90
      },
      "medium": {
        "url": "https://i.ytimg.com/vi/q34q9HBW5M8/mqdefault.jpg",
        "width": 320,
        "height": 180
      },
      "high": {
        "url": "https://i.ytimg.com/vi/q34q9HBW5M8/hqdefault.jpg",
        "width": 480,
        "height": 360
      }
    },
    "channelTitle": "Jordan B Peterson",
    "liveBroadcastContent": "none",
    "publishTime": "2018-10-01T20:33:38Z"
  },
  "_id": "q34q9HBW5M8",
  "publishedAt": "2018-10-01T20:33:38Z",
  "type": "youtube-channel-item",
  "collections": [
    "https://www.youtube.com/channel/UCL_f53ZEJxp8TtlOkHwMV9Q"
  ]
}