{
  "kind": "youtube#searchResult",
  "id": {
    "kind": "youtube#video",
    "videoId": "rdP0dRYN8rk"
  },
  "snippet": {
    "publishedAt": "2017-06-22T17:37:33Z",
    "channelId": "UCUCXWOOz06krkFBsZwH6kHg",
    "title": "Apple 34: conspiracy theory discussion website",
    "description": "Crowd source the truth and fiction to decide where you stand.",
    "thumbnails": {
      "default": {
        "url": "https://i.ytimg.com/vi/rdP0dRYN8rk/default.jpg",
        "width": 120,
        "height": 90
      },
      "medium": {
        "url": "https://i.ytimg.com/vi/rdP0dRYN8rk/mqdefault.jpg",
        "width": 320,
        "height": 180
      },
      "high": {
        "url": "https://i.ytimg.com/vi/rdP0dRYN8rk/hqdefault.jpg",
        "width": 480,
        "height": 360
      }
    },
    "channelTitle": "Jubilee Creates Something Amazing",
    "liveBroadcastContent": "none",
    "publishTime": "2017-06-22T17:37:33Z"
  },
  "_id": "rdP0dRYN8rk",
  "publishedAt": "2017-06-22T17:37:33Z",
  "type": "youtube-channel-item",
  "collections": [
    "https://www.youtube.com/channel/UCUCXWOOz06krkFBsZwH6kHg"
  ]
}