{
  "kind": "youtube#searchResult",
  "etag": "5HVYlm_pKJtlGyGPcZEe7_5-wN4",
  "id": {
    "kind": "youtube#video",
    "videoId": "7Ut_tAzUC1c"
  },
  "snippet": {
    "publishedAt": "2017-06-22T16:56:23Z",
    "channelId": "UCUCXWOOz06krkFBsZwH6kHg",
    "title": "Apple 31: Etsy for slow fashion",
    "description": "Support local artists making sustainable fashion, also allows for coordination of pop up spaces.",
    "thumbnails": {
      "default": {
        "url": "https://i.ytimg.com/vi/7Ut_tAzUC1c/default.jpg",
        "width": 120,
        "height": 90
      },
      "medium": {
        "url": "https://i.ytimg.com/vi/7Ut_tAzUC1c/mqdefault.jpg",
        "width": 320,
        "height": 180
      },
      "high": {
        "url": "https://i.ytimg.com/vi/7Ut_tAzUC1c/hqdefault.jpg",
        "width": 480,
        "height": 360
      }
    },
    "channelTitle": "Jubilee Creates Something Amazing",
    "liveBroadcastContent": "none",
    "publishTime": "2017-06-22T16:56:23Z"
  },
  "_id": "7Ut_tAzUC1c",
  "publishedAt": "2017-06-22T16:56:23Z",
  "collections": [
    "https://www.youtube.com/channel/UCUCXWOOz06krkFBsZwH6kHg"
  ],
  "type": "youtube-channel-item"
}