{
  "kind": "youtube#searchResult",
  "etag": "EYm3DI2x1f8aT9nTJLtnL0x0xxQ",
  "id": {
    "kind": "youtube#video",
    "videoId": "Fyd5c-LUGY8"
  },
  "snippet": {
    "publishedAt": "2019-09-20T19:36:32Z",
    "channelId": "UCUCXWOOz06krkFBsZwH6kHg",
    "title": "FAQ- &quot;Fix the World Fridays&quot;",
    "description": "Me (Jubilee) answering any and all questions on how a tech coop creates a world that works for everyone. I will be going live every Friday 11am PST (right here) ...",
    "thumbnails": {
      "default": {
        "url": "https://i.ytimg.com/vi/Fyd5c-LUGY8/default.jpg",
        "width": 120,
        "height": 90
      },
      "medium": {
        "url": "https://i.ytimg.com/vi/Fyd5c-LUGY8/mqdefault.jpg",
        "width": 320,
        "height": 180
      },
      "high": {
        "url": "https://i.ytimg.com/vi/Fyd5c-LUGY8/hqdefault.jpg",
        "width": 480,
        "height": 360
      }
    },
    "channelTitle": "Jubilee Creates Something Amazing",
    "liveBroadcastContent": "none",
    "publishTime": "2019-09-20T19:36:32Z"
  },
  "_id": "Fyd5c-LUGY8",
  "publishedAt": "2019-09-20T19:36:32Z",
  "collections": [
    "https://www.youtube.com/channel/UCUCXWOOz06krkFBsZwH6kHg"
  ],
  "type": "youtube-channel-item"
}